Metadata-Version: 1.0
Name: newlibcode
Version: 0.1.1
Summary: Sample package for Python-Guide.org
Home-page: UNKNOWN
Author: UNKNOWN
Author-email: UNKNOWN
License: 
